LICENSE
MANIFEST.in
README.md
setup.py
src/mongodb_monitoring.py
src/mongodb_util.py
src/mongodb_util.egg-info/PKG-INFO
src/mongodb_util.egg-info/SOURCES.txt
src/mongodb_util.egg-info/dependency_links.txt
src/mongodb_util.egg-info/not-zip-safe
src/mongodb_util.egg-info/requires.txt
src/mongodb_util.egg-info/top_level.txt
test-cases/mongodb_monitoringut.py
test-cases/mongodb_utilut.py