Metadata-Version: 2.1
Name: mongodb-util
Version: 1.2
Summary: This module provides an easy mechanism to connect to MongoDbalong with various monitoring options that help debug issues at database level
Home-page: UNKNOWN
Author: Aman Mishra
Author-email: aman@switchon.io
License: UNKNOWN
Platform: UNKNOWN
Classifier: Programming Language :: Python :: 3
Classifier: Operating System :: POSIX :: Linux
Provides-Extra: dev
